{"moduleName":null,"summaries":[{"symbol":{"__symbol":0,"members":[]},"metadata":{"__symbolic":"class","members":{"tasks":[{"__symbolic":"property","decorators":[{"__symbolic":"call","expression":{"__symbol":1,"members":[]}}]}],"onAddTask":[{"__symbolic":"property","decorators":[{"__symbolic":"call","expression":{"__symbol":1,"members":[]}}]}],"__ctor__":[{"__symbolic":"constructor"}],"add":[{"__symbolic":"method"}]}},"type":{"summaryKind":1,"type":{"reference":{"__symbol":0,"members":[]},"diDeps":[],"lifecycleHooks":[]},"isComponent":true,"selector":"app-new-task-form","exportAs":null,"inputs":{"tasks":"tasks","onAddTask":"onAddTask"},"outputs":{},"hostListeners":{},"hostProperties":{},"hostAttributes":{},"providers":[],"viewProviders":[],"queries":[],"guards":{},"viewQueries":[],"entryComponents":[],"changeDetection":1,"template":{"ngContentSelectors":[],"encapsulation":0,"styles":[],"animations":[]},"componentViewType":{"__symbol":2,"members":[]},"rendererType":{"__symbol":3,"members":[]},"componentFactory":{"__symbol":4,"members":[]}}}],"symbols":[{"__symbol":0,"name":"NewTaskFormComponent","filePath":"./new-task-form.component"},{"__symbol":1,"name":"Input","filePath":"@angular/core"},{"__symbol":2,"name":"View_NewTaskFormComponent_0","filePath":"./new-task-form.component.ngfactory"},{"__symbol":3,"name":"RenderType_NewTaskFormComponent","filePath":"./new-task-form.component.ngfactory"},{"__symbol":4,"name":"NewTaskFormComponentNgFactory","filePath":"./new-task-form.component.ngfactory"}]}